aws_cfn_update/__init__.py
aws_cfn_update/__main__.py
aws_cfn_update/add_missing_resources.py
aws_cfn_update/add_new_resources.py
aws_cfn_update/cfn_updater.py
aws_cfn_update/cli.py
aws_cfn_update/config_rule_inline_code_updater.py
aws_cfn_update/container_image_updater.py
aws_cfn_update/cron_schedule_expression_updater.py
aws_cfn_update/lambda_inline_code_updater.py
aws_cfn_update/lambda_s3_key_updater.py
aws_cfn_update/latest_ami_updater.py
aws_cfn_update/oidc_provider_thumbprints_updater.py
aws_cfn_update/packer_ami_updater.py
aws_cfn_update/remove_resource.py
aws_cfn_update/replace_references.py
aws_cfn_update/rest_api_body_updater.py
aws_cfn_update/statemachine_updater.py
aws_cfn_update-0.12.1.dist-info/LICENSE
aws_cfn_update-0.12.1.dist-info/METADATA
aws_cfn_update-0.12.1.dist-info/WHEEL
aws_cfn_update-0.12.1.dist-info/entry_points.txt
aws_cfn_update-0.12.1.dist-info/top_level.txt
aws_cfn_update-0.12.1.dist-info/zip-safe
aws_cfn_update-0.12.1.dist-info/RECORD
