Metadata-Version: 2.1
Name: aws-cfn-update
Version: 0.12.1
Summary: Programmatically update CloudFormation templates
Home-page: https://github.com/binxio/aws-cfn-update
Author: Mark van Holsteijn
Author-email: mark.vanholsteijn@xebia.com
License: BSD 3-Clause License
Classifier: Development Status :: 5 - Production/Stable
Classifier: Environment :: Console
Classifier: Intended Audience :: Developers
Classifier: License :: OSI Approved :: BSD License
Classifier: Operating System :: POSIX
Classifier: Operating System :: MacOS
Classifier: Operating System :: Unix
Classifier: Programming Language :: Python :: 3
Requires-Python: >=3.9
License-File: LICENSE
Requires-Dist: click
Requires-Dist: boto3
Requires-Dist: cfn-flip
Requires-Dist: pytz
Requires-Dist: croniter
Requires-Dist: tzlocal
Requires-Dist: ruamel.yaml >=0.17.0
Requires-Dist: requests
Requires-Dist: jsonmerge
Requires-Dist: cryptography
